immlib/__init__.py
immlib/_init.py
immlib/_version.py
immlib/doc/__init__.py
immlib/doc/_core.py
immlib/iolib/__init__.py
immlib/iolib/_core.py
immlib/pathlib/__init__.py
immlib/pathlib/_cache.py
immlib/pathlib/_core.py
immlib/pathlib/_osf.py
immlib/test/__init__.py
immlib/test/__main__.py
immlib/test/doc/__init__.py
immlib/test/doc/test_core.py
immlib/test/iolib/__init__.py
immlib/test/iolib/test_core.py
immlib/test/pathlib/__init__.py
immlib/test/pathlib/test_core.py
immlib/test/pathlib/test_osf.py
immlib/test/types/__init__.py
immlib/test/types/test_core.py
immlib/test/util/__init__.py
immlib/test/util/test_core.py
immlib/test/util/test_numeric.py
immlib/test/util/test_quantity.py
immlib/test/util/test_url.py
immlib/test/workflow/__init__.py
immlib/test/workflow/test_core.py
immlib/test/workflow/test_plantype.py
immlib/types/__init__.py
immlib/types/_core.py
immlib/util/__init__.py
immlib/util/_core.py
immlib/util/_numeric.py
immlib/util/_quantity.py
immlib/util/_url.py
immlib/workflow/__init__.py
immlib/workflow/_core.py
immlib/workflow/_plantype.py
immlib-1.0.0.dev2.dist-info/licenses/LICENSE
immlib-1.0.0.dev2.dist-info/METADATA
immlib-1.0.0.dev2.dist-info/WHEEL
immlib-1.0.0.dev2.dist-info/top_level.txt
immlib-1.0.0.dev2.dist-info/RECORD
